mnllib/__init__.py
mnllib/bis/__init__.py
mnllib/bis/compression.py
mnllib/bis/consts.py
mnllib/bis/managers.py
mnllib/bis/misc.py
mnllib/bis/script.py
mnllib/bis/text.py
mnllib/consts.py
mnllib/dt/__init__.py
mnllib/dt/consts.py
mnllib/dt/managers.py
mnllib/dt/misc.py
mnllib/dt/script.py
mnllib/dt/text.py
mnllib/managers.py
mnllib/misc.py
mnllib/n3ds/__init__.py
mnllib/n3ds/consts.py
mnllib/n3ds/misc.py
mnllib/nds/__init__.py
mnllib/nds/consts.py
mnllib/py.typed
mnllib/script.py
mnllib/utils.py
mnllib-0.2.3.dist-info/LICENSE
mnllib-0.2.3.dist-info/METADATA
mnllib-0.2.3.dist-info/WHEEL
mnllib-0.2.3.dist-info/RECORD
