Metadata-Version: 2.3
Name: mnllib
Version: 0.2.3
Summary: Python library for the Mario & Luigi games.
License: LGPL-3.0-or-later
Author: Dimitar Dimitrov
Author-email: dmtrdmtrov@gmail.com
Requires-Python: >=3.12,<4.0
Classifier: License :: OSI Approved :: GNU Lesser General Public License v3 or later (LGPLv3+)
Classifier: Programming Language :: Python :: 3
Classifier: Programming Language :: Python :: 3.12
Classifier: Programming Language :: Python :: 3.13
Requires-Dist: pymsbmnl (>=1.1.0,<2.0.0)
Requires-Dist: structured-classes (>=3.1.0,<4.0.0)
Project-URL: Repository, https://github.com/MnL-Modding/mnllib.py
